spectroscopytools/__init__.py
spectroscopytools/uvvis.py
spectroscopy_toolbox-0.0.1.dist-info/LICENSE
spectroscopy_toolbox-0.0.1.dist-info/METADATA
spectroscopy_toolbox-0.0.1.dist-info/WHEEL
spectroscopy_toolbox-0.0.1.dist-info/top_level.txt
spectroscopy_toolbox-0.0.1.dist-info/RECORD
